micawber/__init__.py
micawber/cache.py
micawber/compat.py
micawber/exceptions.py
micawber/parsers.py
micawber/providers.py
micawber/test_utils.py
micawber/tests.py
micawber/contrib/__init__.py
micawber/contrib/mcflask.py
micawber/contrib/providers.py
micawber/contrib/mcdjango/__init__.py
micawber/contrib/mcdjango/models.py
micawber/contrib/mcdjango/providers.py
micawber/contrib/mcdjango/mcdjango_tests/__init__.py
micawber/contrib/mcdjango/mcdjango_tests/models.py
micawber/contrib/mcdjango/mcdjango_tests/tests.py
micawber/contrib/mcdjango/templates/micawber/link.html
micawber/contrib/mcdjango/templates/micawber/photo.html
micawber/contrib/mcdjango/templates/micawber/rich.html
micawber/contrib/mcdjango/templates/micawber/video.html
micawber/contrib/mcdjango/templatetags/__init__.py
micawber/contrib/mcdjango/templatetags/micawber_tags.py
micawber-0.6.2.dist-info/licenses/LICENSE
micawber-0.6.2.dist-info/METADATA
micawber-0.6.2.dist-info/WHEEL
micawber-0.6.2.dist-info/top_level.txt
micawber-0.6.2.dist-info/RECORD
