Metadata-Version: 2.4
Name: micawber
Version: 0.6.2
Summary: a small library for extracting rich content from urls
Author-email: Charles Leifer <coleifer@gmail.com>
Project-URL: Repository, https://github.com/coleifer/micawber
Project-URL: Documentation, https://micawber.readthedocs.io/
Classifier: Programming Language :: Python :: 2
Classifier: Programming Language :: Python :: 3
Classifier: Topic :: Software Development :: Libraries :: Python Modules
License-File: LICENSE
Requires-Dist: lxml
Requires-Dist: beautifulsoup4
Provides-Extra: cache
Requires-Dist: redis>=3.0.0; extra == "cache"
Dynamic: license-file
